nonebot_plugin_arcaea/__init__.py
nonebot_plugin_arcaea/api/__init__.py
nonebot_plugin_arcaea/api/_base.py
nonebot_plugin_arcaea/api/adapters/__init__.py
nonebot_plugin_arcaea/api/adapters/botarcapi/__init__.py
nonebot_plugin_arcaea/api/adapters/botarcapi/utils.py
nonebot_plugin_arcaea/api/adapters/botarcapi/v4/__init__.py
nonebot_plugin_arcaea/api/adapters/botarcapi/v4/_call_api.py
nonebot_plugin_arcaea/api/adapters/botarcapi/v4/main.py
nonebot_plugin_arcaea/api/adapters/estertion/__init__.py
nonebot_plugin_arcaea/api/adapters/estertion/_call_api.py
nonebot_plugin_arcaea/api/adapters/estertion/main.py
nonebot_plugin_arcaea/api/resolver.py
nonebot_plugin_arcaea/api/utils.py
nonebot_plugin_arcaea/config.py
nonebot_plugin_arcaea/crud/__init__.py
nonebot_plugin_arcaea/crud/crud_user.py
nonebot_plugin_arcaea/db/__init__.py
nonebot_plugin_arcaea/db/init_db.sql
nonebot_plugin_arcaea/db/load_db.py
nonebot_plugin_arcaea/exceptions.py
nonebot_plugin_arcaea/handlers/__init__.py
nonebot_plugin_arcaea/handlers/auth.py
nonebot_plugin_arcaea/handlers/b30.py
nonebot_plugin_arcaea/handlers/best.py
nonebot_plugin_arcaea/handlers/bind.py
nonebot_plugin_arcaea/handlers/config.py
nonebot_plugin_arcaea/handlers/help.py
nonebot_plugin_arcaea/handlers/info.py
nonebot_plugin_arcaea/handlers/pre.py
nonebot_plugin_arcaea/handlers/recent.py
nonebot_plugin_arcaea/handlers/songinfo.py
nonebot_plugin_arcaea/main.py
nonebot_plugin_arcaea/matcher.py
nonebot_plugin_arcaea/messages/__init__.py
nonebot_plugin_arcaea/messages/main.py
nonebot_plugin_arcaea/messages/text_utils.py
nonebot_plugin_arcaea/messages/themes/__init__.py
nonebot_plugin_arcaea/messages/themes/_base.py
nonebot_plugin_arcaea/messages/themes/pkgs/__init__.py
nonebot_plugin_arcaea/messages/themes/pkgs/theme_default/__init__.py
nonebot_plugin_arcaea/messages/themes/pkgs/theme_default/assets/Roboto-Bold.ttf
nonebot_plugin_arcaea/messages/themes/pkgs/theme_default/assets/Roboto-Regular.ttf
nonebot_plugin_arcaea-0.2.1.dist-info/WHEEL
nonebot_plugin_arcaea-0.2.1.dist-info/METADATA
nonebot_plugin_arcaea-0.2.1.dist-info/LICENSE
nonebot_plugin_arcaea-0.2.1.dist-info/RECORD
