Metadata-Version: 2.1
Name: nonebot-plugin-arcaea
Version: 0.2.1
Summary: An arcaea rhythm game score-querying bot plugin for nonebot2.
License: MIT
Keywords: bot,qq,plugin,onebot,arcaea
Author-email: iyume <iyumelive@gmail.com>
Requires-Python: >=3.7
Classifier: License :: OSI Approved :: MIT License
Classifier: Programming Language :: Python :: 3
Classifier: Programming Language :: Python :: 3.7
Classifier: Programming Language :: Python :: 3.8
Classifier: Programming Language :: Python :: 3.9
Requires-Dist: brotli~=1.0
Requires-Dist: httpx~=0.17
Requires-Dist: nonebot2~=2.0.0a9
Requires-Dist: pillow~=8.2
Project-URL: documentation, https://github.com/iyume/nonebot-plugin-arcaea/blob/master/README.md
Project-URL: homepage, https://github.com/iyume/nonebot-plugin-arcaea
Project-URL: repository, https://github.com/iyume/nonebot-plugin-arcaea
